enhance_long/__init__.py
enhance_long/baichuan2_forward.py
enhance_long/chatglm3_forward.py
enhance_long/enhance_llama.py
enhance_long/replace_llama_attention.py
enhance_long/requirements.txt
enhance_long-0.0.8.dist-info/METADATA
enhance_long-0.0.8.dist-info/WHEEL
enhance_long-0.0.8.dist-info/licenses/LICENSE
enhance_long-0.0.8.dist-info/RECORD
