Metadata-Version: 2.1
Name: enhance-long
Version: 0.0.8
Summary: The tool integrates the lowest cost and highest performance methods to enhance the ability of large languages to process long contexts
Project-URL: Homepage, https://github.com/MrYxJ/enhance_long
Author-email: MrYXJ <yxj2017@gmail.com>
License: MIT License
License-File: LICENSE
Classifier: License :: OSI Approved :: MIT License
Classifier: Operating System :: OS Independent
Classifier: Programming Language :: Python :: 3
Requires-Python: >=3.6
Requires-Dist: einops
Requires-Dist: flash-attn
Requires-Dist: torch>=1.1.0
Requires-Dist: tqdm
Requires-Dist: transformers>=4.35.2
